langchain_openai/__init__.py
langchain_openai/py.typed
langchain_openai/chat_models/__init__.py
langchain_openai/chat_models/azure.py
langchain_openai/chat_models/base.py
langchain_openai/embeddings/__init__.py
langchain_openai/embeddings/azure.py
langchain_openai/embeddings/base.py
langchain_openai/llms/__init__.py
langchain_openai/llms/azure.py
langchain_openai/llms/base.py
langchain_openai/output_parsers/__init__.py
langchain_openai/output_parsers/tools.py
langchain_openai_aipy-0.3.9.dist-info/METADATA
langchain_openai_aipy-0.3.9.dist-info/WHEEL
langchain_openai_aipy-0.3.9.dist-info/top_level.txt
langchain_openai_aipy-0.3.9.dist-info/RECORD
