Metadata-Version: 2.4
Name: langchain-openai-aipy
Version: 0.3.9
Summary: An integration package connecting OpenAI and LangChain
Author-email: The QPYPI Team <qpypi@qpython.org>
License: MIT AND (Apache-2.0 OR BSD-2-Clause)
Project-URL: Homepage, https://qpypi.qpython.org/project/langchain-openai-aipy/
Classifier: Intended Audience :: Developers
Classifier: Intended Audience :: Education
Classifier: Intended Audience :: Information Technology
Classifier: Intended Audience :: End Users/Desktop
Classifier: License :: OSI Approved :: Apache Software License
Classifier: Operating System :: Android
Classifier: Programming Language :: Python
Classifier: Programming Language :: Python :: 3.12
Classifier: Topic :: Software Development
Requires-Python: ==3.12.*
Requires-Dist: openai-aipy
Requires-Dist: tiktoken-qpython
